NiukeXiaoshouGangQiuzhiJingyanFenxiang20212022Fix1/README.md
NiukeXiaoshouGangQiuzhiJingyanFenxiang20212022Fix1/__init__.py
NiukeXiaoshouGangQiuzhiJingyanFenxiang20212022Fix1/__main__.py
NiukeXiaoshouGangQiuzhiJingyanFenxiang20212022Fix1/file.epub
NiukeXiaoshouGangQiuzhiJingyanFenxiang20212022Fix1/index.html
NiukeXiaoshouGangQiuzhiJingyanFenxiang20212022Fix1/css/__init__.py
NiukeXiaoshouGangQiuzhiJingyanFenxiang20212022Fix1/css/annotations.css
NiukeXiaoshouGangQiuzhiJingyanFenxiang20212022Fix1/css/main.css
NiukeXiaoshouGangQiuzhiJingyanFenxiang20212022Fix1/css/normalize.css
NiukeXiaoshouGangQiuzhiJingyanFenxiang20212022Fix1/css/popup.css
NiukeXiaoshouGangQiuzhiJingyanFenxiang20212022Fix1/font/__init__.py
NiukeXiaoshouGangQiuzhiJingyanFenxiang20212022Fix1/font/fontello.eot
NiukeXiaoshouGangQiuzhiJingyanFenxiang20212022Fix1/font/fontello.svg
NiukeXiaoshouGangQiuzhiJingyanFenxiang20212022Fix1/font/fontello.ttf
NiukeXiaoshouGangQiuzhiJingyanFenxiang20212022Fix1/font/fontello.woff
NiukeXiaoshouGangQiuzhiJingyanFenxiang20212022Fix1/img/__init__.py
NiukeXiaoshouGangQiuzhiJingyanFenxiang20212022Fix1/img/annotator-glyph-sprite.png
NiukeXiaoshouGangQiuzhiJingyanFenxiang20212022Fix1/img/annotator-icon-sprite.png
NiukeXiaoshouGangQiuzhiJingyanFenxiang20212022Fix1/img/apple-touch-icon.png
NiukeXiaoshouGangQiuzhiJingyanFenxiang20212022Fix1/img/cancelfullscreen.png
NiukeXiaoshouGangQiuzhiJingyanFenxiang20212022Fix1/img/close.png
NiukeXiaoshouGangQiuzhiJingyanFenxiang20212022Fix1/img/fullscreen.png
NiukeXiaoshouGangQiuzhiJingyanFenxiang20212022Fix1/img/loader.gif
NiukeXiaoshouGangQiuzhiJingyanFenxiang20212022Fix1/img/menu-icon.png
NiukeXiaoshouGangQiuzhiJingyanFenxiang20212022Fix1/img/save.png
NiukeXiaoshouGangQiuzhiJingyanFenxiang20212022Fix1/img/saved.png
NiukeXiaoshouGangQiuzhiJingyanFenxiang20212022Fix1/img/settings-s.png
NiukeXiaoshouGangQiuzhiJingyanFenxiang20212022Fix1/img/settings.png
NiukeXiaoshouGangQiuzhiJingyanFenxiang20212022Fix1/img/star.png
niuke_xiaoshou_gang_qiuzhi_jingyan_fenxiang_2021_2022_fix1-2025.3.25.1.dist-info/METADATA
niuke_xiaoshou_gang_qiuzhi_jingyan_fenxiang_2021_2022_fix1-2025.3.25.1.dist-info/WHEEL
niuke_xiaoshou_gang_qiuzhi_jingyan_fenxiang_2021_2022_fix1-2025.3.25.1.dist-info/entry_points.txt
niuke_xiaoshou_gang_qiuzhi_jingyan_fenxiang_2021_2022_fix1-2025.3.25.1.dist-info/top_level.txt
niuke_xiaoshou_gang_qiuzhi_jingyan_fenxiang_2021_2022_fix1-2025.3.25.1.dist-info/RECORD
